README.md
setup.py
ynitdb/__init__.py
ynitdb.egg-info/PKG-INFO
ynitdb.egg-info/SOURCES.txt
ynitdb.egg-info/dependency_links.txt
ynitdb.egg-info/top_level.txt