Metadata-Version: 2.1
Name: ynitdb
Version: 0.0.5
Summary: A tiny non-volatile dictionary handler for python
Home-page: https://thevoxel.net/projects/ynitdb
Author: Vorap
Author-email: vorap@thevoxel.net
License: GNU GPLv3
Platform: UNKNOWN
Classifier: Programming Language :: Python :: 3.7
Classifier: Operating System :: OS Independent
